4 Bit Adder FPGA/testbench.v
module test;
    
    // input to be bound
    reg [3:0] rin1, rin2;
    reg clk, rcin;
    
    // output to be bound
    wire wcout;
    wire [3:0] wout;

    // register to store configuration
    reg [31:0] read [5:0];
    
    // generate clock signal although not required for combinational circuit (adder in this case)
    initial clk = 0;
    always #10 clk = ~clk;
    
    // bind i/o ports
    adder_4_bit inst_adder_4_bit(.clock(clk), .in1(rin1), .in2(rin2), .cin(rcin), .out(wout), .cout(wcout));
    
    // read up lookup table from file : configure.mem
    initial $readmemh("configure.mem", read);
    
    // store lookup table and configuration data in the module
    initial begin
        inst_adder_4_bit.LT00.mem[31:0] <= read[0];
        inst_adder_4_bit.LT00.mem[32] <= read[1][0];

        inst_adder_4_bit.LT01.mem[31:0] <= read[0];
        inst_adder_4_bit.LT01.mem[32] <= read[1][0];

        inst_adder_4_bit.LT10.mem[31:0] <= read[2];
        inst_adder_4_bit.LT10.mem[32] <= read[3][0];

        inst_adder_4_bit.LT11.mem[31:0] <= read[2];
        inst_adder_4_bit.LT11.mem[32] <= read[3][0];

        inst_adder_4_bit.LT20.mem[31:0] <= read[4];
        inst_adder_4_bit.LT20.mem[32] <= read[5][0];

        inst_adder_4_bit.LT21.mem[31:0] <= read[4];
        inst_adder_4_bit.LT21.mem[32] <= read[5][0];
    end

    // checking for different test cases
    integer i;
    initial
        begin
            rin1 = 4'b0000;
            rin2 = 4'b0000;
            rcin = 1'b0;
            #10
            $display(" in1    in2   cin     out  cout");
            $display(" %b   %b   %b  =>  %b  %b", rin1, rin2, rcin, wout, wcout);
            rin1 = 4'b0001;
            rin2 = 4'b0000;
            rcin = 1'b1;
            #10
            $display(" %b   %b   %b  =>  %b  %b", rin1, rin2, rcin, wout, wcout);
            rin1 = 4'b1111;
            rin2 = 4'b1000;
            rcin = 1'b0;
            #10
            $display(" %b   %b   %b  =>  %b  %b", rin1, rin2, rcin, wout, wcout);
            rin1 = 4'b1111;
            rin2 = 4'b1111;
            rcin = 1'b1;
            #10
            $display(" %b   %b   %b  =>  %b  %b", rin1, rin2, rcin, wout, wcout); 
            rin1 = 4'b1111;
            rin2 = 4'b1111;
            rcin = 1'b0;
            #10
            $display(" %b   %b   %b  =>  %b  %b", rin1, rin2, rcin, wout, wcout); 
            rin1 = 4'b1010;
            rin2 = 4'b0101;
            rcin = 1'b0;
            #10
            $display(" %b   %b   %b  =>  %b  %b", rin1, rin2, rcin, wout, wcout);  
            rin1 = 4'b1010;
            rin2 = 4'b0101;
            rcin = 1'b1;
            #10
            $display(" %b   %b   %b  =>  %b  %b", rin1, rin2, rcin, wout, wcout);  
        end

    // generate vcd file
    initial begin
        $dumpfile("l5.vcd");
        $dumpvars;
    end

    // declaring finish time as we used always block for generating clock signal
    initial
        #1000 $finish;
endmodule

4 Bit Adder FPGA/FPGA.v
module logic_tile(out, clock, in1, in2, in3, in4, in5);
    // declaring input output
    input clock, in1, in2, in3, in4, in5;
    output out;
    // declaring memory to store lookup table
    reg [32:0] mem;
    // declaring memory to store intermediate value. used reg instead of wire because it has been used in flip-flop that way.
    // reg d;
    wire d;
    // declaring flip flop
    reg q, qbar;
    always@(posedge clock)
        begin
            q <= d;
            qbar = !d;
        end
    // getting output of LUT through behavioral modelling using blocking assignment i.e combinational design. It can be realized using the rom model with the help of a multiplexer. 
    integer x;
    initial x = {in5, in4, in3, in2, in1};
    assign d = mem[x];

    always@(in5, in4, in3, in2, in1)
        begin
            x <= {in5, in4, in3, in2, in1};
        end

    // depending upon the mux control value, output has been given as ff output for mux control 1 and combinational output for mux control 0.
    assign out = (mem[32] & q) | ((~mem[32]) & d);
endmodule

module switch_box_4x4(out, in);
    // input output declaration
    input [3:0] in;
    output [3:0] out;
    // declaring memory to store configuration of the switch_box_4x4
    reg [15:0] configure;
    // assigning output using simple combinational logic on the basis of configuration
    assign out[0] = (configure[0] & in[0]) | (configure[1] & in[1]) | (configure[2] & in[2]) | (configure[3] & in[3]);
    assign out[1] = (configure[4] & in[0]) | (configure[5] & in[1]) | (configure[6] & in[2]) | (configure[7] & in[3]);
    assign out[2] = (configure[8] & in[0]) | (configure[9] & in[1]) | (configure[10] & in[2]) | (configure[11] & in[3]);
    assign out[3] = (configure[12] & in[0]) | (configure[13] & in[1]) | (configure[14] & in[2]) | (configure[15] & in[3]);
endmodule

// code for lab5
// 4 bit adder with carry in and carry out

module adder_4_bit(clock, in1, in2, cin, out, cout);
    // input output declaration
    input [3:0] in1, in2;
    input clock, cin;
    output [3:0] out;
    output cout;
    // declaring memory to store configuration of 3 different logic tiles
    reg [32:0] mem0, mem1, mem2;
    // declaring wires to be used in the circuit in intermediate parts
    wire w20;
    // combinational circuit design using structural statements
    logic_tile LT00(out[0], clock, cin, in2[0], in2[1], in1[0], in1[1]);
    logic_tile LT10(out[1], clock, cin, in2[0], in2[1], in1[0], in1[1]);
    logic_tile LT20(w20, clock, cin, in2[0], in2[1], in1[0], in1[1]);
    logic_tile LT01(out[2], clock, w20, in2[2], in2[3], in1[2], in1[3]);
    logic_tile LT11(out[3], clock, w20, in2[2], in2[3], in1[2], in1[3]);
    logic_tile LT21(cout, clock, w20, in2[2], in2[3], in1[2], in1[3]);
endmodule

4 Bit Adder FPGA/l5.vcd
$date
	Sun Nov 08 17:11:15 2020
$end
$version
	Icarus Verilog
$end
$timescale
	1s
$end
$scope module switch_box_4x4 $end
$var wire 4 ! in [3:0] $end
$var wire 4 " out [3:0] $end
$var reg 16 # configure [15:0] $end
$upscope $end
$scope module test $end
$var wire 4 $ wout [3:0] $end
$var wire 1 % wcout $end
$var reg 1 & clk $end
$var reg 1 ' rcin $end
$var reg 4 ( rin1 [3:0] $end
$var reg 4 ) rin2 [3:0] $end
$scope module inst_adder_4_bit $end
$var wire 1 ' cin $end
$var wire 1 & clock $end
$var wire 4 * in1 [3:0] $end
$var wire 4 + in2 [3:0] $end
$var wire 1 , w20 $end
$var wire 4 - out [3:0] $end
$var wire 1 % cout $end
$scope module LT00 $end
$var wire 1 & clock $end
$var wire 1 ' in1 $end
$var wire 1 . in2 $end
$var wire 1 / in3 $end
$var wire 1 0 in4 $end
$var wire 1 1 in5 $end
$var wire 1 2 out $end
$var wire 1 3 d $end
$var reg 33 4 mem [32:0] $end
$var reg 1 5 q $end
$var reg 1 6 qbar $end
$var integer 32 7 x [31:0] $end
$upscope $end
$scope module LT01 $end
$var wire 1 & clock $end
$var wire 1 8 in2 $end
$var wire 1 9 in3 $end
$var wire 1 : in4 $end
$var wire 1 ; in5 $end
$var wire 1 < out $end
$var wire 1 , in1 $end
$var wire 1 = d $end
$var reg 33 > mem [32:0] $end
$var reg 1 ? q $end
$var reg 1 @ qbar $end
$var integer 32 A x [31:0] $end
$upscope $end
$scope module LT10 $end
$var wire 1 & clock $end
$var wire 1 ' in1 $end
$var wire 1 B in2 $end
$var wire 1 C in3 $end
$var wire 1 D in4 $end
$var wire 1 E in5 $end
$var wire 1 F out $end
$var wire 1 G d $end
$var reg 33 H mem [32:0] $end
$var reg 1 I q $end
$var reg 1 J qbar $end
$var integer 32 K x [31:0] $end
$upscope $end
$scope module LT11 $end
$var wire 1 & clock $end
$var wire 1 L in2 $end
$var wire 1 M in3 $end
$var wire 1 N in4 $end
$var wire 1 O in5 $end
$var wire 1 P out $end
$var wire 1 , in1 $end
$var wire 1 Q d $end
$var reg 33 R mem [32:0] $end
$var reg 1 S q $end
$var reg 1 T qbar $end
$var integer 32 U x [31:0] $end
$upscope $end
$scope module LT20 $end
$var wire 1 & clock $end
$var wire 1 ' in1 $end
$var wire 1 V in2 $end
$var wire 1 W in3 $end
$var wire 1 X in4 $end
$var wire 1 Y in5 $end
$var wire 1 , out $end
$var wire 1 Z d $end
$var reg 33 [ mem [32:0] $end
$var reg 1 \ q $end
$var reg 1 ] qbar $end
$var integer 32 ^ x [31:0] $end
$upscope $end
$scope module LT21 $end
$var wire 1 & clock $end
$var wire 1 , in1 $end
$var wire 1 _ in2 $end
$var wire 1 ` in3 $end
$var wire 1 a in4 $end
$var wire 1 b in5 $end
$var wire 1 % out $end
$var wire 1 c d $end
$var reg 33 d mem [32:0] $end
$var reg 1 e q $end
$var reg 1 f qbar $end
$var integer 32 g x [31:0] $end
$upscope $end
$upscope $end
$upscope $end
$enddefinitions $end
#0
$dumpvars
b0 g
xf
xe
b11111110111110001110000010000000 d
0c
0b
0a
0`
0_
b0 ^
x]
x\
b11111110111110001110000010000000 [
0Z
0Y
0X
0W
0V
b0 U
xT
xS
b11100001100001110001111001111000 R
0Q
0P
0O
0N
0M
0L
b0 K
xJ
xI
b11100001100001110001111001111000 H
0G
0F
0E
0D
0C
0B
b0 A
x@
x?
b10011001011001101001100101100110 >
0=
0<
0;
0:
09
08
b0 7
x6
x5
b10011001011001101001100101100110 4
03
02
01
00
0/
0.
b0 -
0,
b0 +
b0 *
b0 )
b0 (
0'
0&
0%
b0 $
bx #
bx "
bz !
$end
#10
b10 $
b10 -
1F
b1001 7
1G
b1001 K
b1001 ^
05
0I
0\
0?
0S
0e
10
1D
1X
16
1J
1]
1@
1T
1f
1'
b1 (
b1 *
1&
#20
1<
1%
b111 $
b111 -
12
1=
b11100 A
b11100 U
1c
b11100 g
13
b11000 7
b11000 K
b11000 ^
19
1M
1`
11
1E
1Y
1:
1;
1N
1O
1a
1b
0'
b1000 )
b1000 +
b1111 (
b1111 *
0&
#30
1<
b1111 $
b1111 -
1P
1,
1=
b11111 A
1Q
b11111 U
b11111 g
b11111 7
b11111 K
1Z
b11111 ^
1e
1?
1I
15
1.
1/
1B
1C
1V
1W
18
1L
1_
0f
0@
0J
06
1'
b1111 )
b1111 +
1&
#40
b1110 $
b1110 -
02
03
b11110 7
b11110 K
b11110 ^
0'
0&
#50
0%
0c
12
0,
1<
b1111 $
b1111 -
1P
13
b10010 7
b10010 K
0Z
b10010 ^
1=
b10010 A
1Q
b10010 U
b10010 g
05
1\
1S
0/
0C
0W
09
0M
0`
00
0D
0X
0:
0N
0a
16
0]
0T
b101 )
b101 +
b1010 (
b1010 *
1&
#60
0<
0P
1%
0=
b10011 A
0Q
b10011 U
1c
b10011 g
02
b0 $
b0 -
0F
1,
03
b10011 7
0G
b10011 K
1Z
b10011 ^
1'
0&
#70
0S
0?
0I
1T
1@
1J
1&
